deploy_utils/__init__.py
deploy_utils/config.py
deploy_utils/ec2.py
deploy_utils/example_script.py
deploy_utils/fab.py
deploy_utils/templates/init_test_db.sql
deploy_utils/templates/pg_hba.conf
deploy_utils/templates/test_amazon_linux.ini
deploy_utils/templates/test_centos6.ini
deploy_utils/templates/test_conf.ini
deploy_utils/templates/test_conf_helper.ini
deploy_utils/templates/user-init
deploy_utils/tests/__init__.py
deploy_utils/tests/integration/__init__.py
deploy_utils/tests/integration/ec2_base.py
deploy_utils/tests/integration/test_amazon_linux.py
deploy_utils/tests/integration/test_centos6.py
deploy_utils/tests/integration/test_config.py
deploy_utils/tests/unit/__init__.py
deploy_utils-1.0.1.dist-info/LICENSE
deploy_utils-1.0.1.dist-info/METADATA
deploy_utils-1.0.1.dist-info/WHEEL
deploy_utils-1.0.1.dist-info/entry_points.txt
deploy_utils-1.0.1.dist-info/top_level.txt
deploy_utils-1.0.1.dist-info/RECORD
