Metadata-Version: 2.1
Name: deploy-utils
Version: 1.0.1
Summary: Utilities for deploying projects to EC2
Home-page: https://github.com/evansiroky/deploy_utils
Author: Evan Siroky
License: MIT
Keywords: AWS Fabric deployment
Platform: UNKNOWN
Classifier: Development Status :: 3 - Alpha
Classifier: License :: OSI Approved :: MIT License
Classifier: Programming Language :: Python :: 2.7
Classifier: Programming Language :: Python :: 3
Requires-Dist: boto3 (>=1.9.101)
Requires-Dist: fabric (<2,>=1.10.1)
Requires-Dist: django-fab-deploy (>=0.7.5)
